coney/__init__.py
coney/broker.py
coney/py.typed
coney-0.1.4.dist-info/WHEEL
coney-0.1.4.dist-info/METADATA
coney-0.1.4.dist-info/RECORD
